{
  "entity_groups": {
    "向买受人交付标的物或者交付提取标的物的单证": [
      "向买受人交付标的物或者交付提取标的物的单证",
      "交货",
      "交付货物",
      "货物交付",
      "供货",
      "交付标的物",
      "标的物交付",
      "交付",
      "提供货物",
      "发货"
    ],
    "约定的时间交付标的物": [
      "约定的时间交付标的物",
      "交货时间",
      "交付时间",
      "交付期限",
      "交货期限",
      "交货日期",
      "交货期",
      "供货时间",
      "发货时间",
      "交付日期",
      "交付标的物的时间",
      "交货时间与地点",
      "交付"
    ],
    "约定的地点交付标的物": [
      "约定的地点交付标的物",
      "交货地点",
      "交付地点",
      "交付标的物的地点",
      "交货地址",
      "送货地点",
      "交货时间与地点",
      "交付"
    ],
    "约定的质量要求交付标的物": [
      "约定的质量要求交付标的物",
      "质量标准",
      "质量要求",
      "质量符合",
      "质量合格",
      "质量保证",
      "质量",
      "产品质量",
      "质量满足",
      "符合质量要求",
      "标的物质量"
    ],
    "约定的包装方式交付标的物": [
      "约定的包装方式交付标的物",
      "包装要求",
      "包装方式",
      "包装",
      "产品包装",
      "包装标准",
      "包装标识"
    ],
    "约定的数额": [
      "约定的数额",
      "金额",
      "总金额",
      "合同总金额",
      "货款",
      "价款",
      "单价",
      "总价",
      "数额",
      "合同金额",
      "价格"
    ],
    "支付方式支付价款": [
      "支付方式支付价款",
      "支付价款",
      "付款方式",
      "支付货款",
      "付款",
      "支付",
      "货款支付",
      "价款支付",
      "结算",
      "支付方式"
    ],
    "约定的时间支付价款": [
      "约定的时间支付价款",
      "付款时间",
      "支付时间",
      "付款期限",
      "付款日期",
      "支付期限",
      "付款",
      "支付价款",
      "货款支付时间",
      "结算时间"
    ],
    "该说明的质量要求": [
      "该说明的质量要求",
      "质量标准",
      "质量要求",
      "质量符合",
      "质量保证",
      "质量合格",
      "质量",
      "产品质量",
      "说明的质量要求",
      "的质量要求"
    ],
    "的检验期限内检验": [
      "的检验期限内检验",
      "验收",
      "检验",
      "检验期限",
      "验收期限",
      "验收期",
      "验收合格",
      "收货检验",
      "货到验收",
      "质量检验",
      "检验合格",
      "进行验收",
      "完成验收",
      "清点",
      "进行检查",
      "核对"
    ],
    "于买受人": [
      "于买受人",
      "买方",
      "买受人",
      "甲方"
    ],
    "的义务": [
      "的义务",
      "义务",
      "责任",
      "职责",
      "负责",
      "承担",
      "有义务"
    ],
    "属于出卖人": [
      "属于出卖人",
      "出卖人",
      "卖方",
      "乙方",
      "供货方",
      "销售方"
    ],
    "的时间交付标的物": [
      "的时间交付标的物",
      "交货时间",
      "交付时间",
      "交付期限",
      "交货期限",
      "交货日期",
      "交货期",
      "供货时间",
      "发货时间",
      "交付标的物",
      "标的物交付",
      "交付"
    ],
    "的地点交付标的物": [
      "的地点交付标的物",
      "交货地点",
      "交付地点",
      "交货地址",
      "送货地点",
      "交付标的物",
      "标的物交付",
      "交付"
    ],
    "的质量要求交付标的物": [
      "的质量要求交付标的物",
      "质量标准",
      "质量要求",
      "质量符合",
      "质量合格",
      "质量保证",
      "产品质量",
      "交付标的物的质量",
      "标的物质量"
    ],
    "违约责任": [
      "违约责任",
      "违约",
      "违约赔偿",
      "违约金",
      "赔偿损失",
      "赔偿",
      "承担违约责任",
      "违约责任承担",
      "违约处置"
    ],
    "的包装方式交付标的物": [
      "的包装方式交付标的物",
      "包装要求",
      "包装方式",
      "包装",
      "产品包装",
      "包装标准",
      "包装标识",
      "的包装方式",
      "包装"
    ],
    "的数额": [
      "的数额",
      "金额",
      "总金额",
      "合同总金额",
      "货款",
      "价款",
      "单价",
      "总价",
      "数额",
      "合同金额",
      "价格",
      "款项"
    ],
    "的时间支付价款": [
      "的时间支付价款",
      "付款时间",
      "支付时间",
      "付款期限",
      "付款日期",
      "支付期限",
      "付款",
      "支付价款",
      "支付货款",
      "货款支付",
      "结算期限"
    ]
  }
}